.gitignore
INFOandTODO.md
LICENSE
MANIFEST.in
README.md
VERSION
appendix.md
pyproject.toml
setup.cfg
setup.py
.github/workflows/publish-to-pypi.yml
.github/workflows/uhelp_autodeb.yml
images/cyber_style.png
images/default_style.png
images/fruits_style.png
images/retro2_style.png
images/retro_style.png
images/simple_style.png
images/uhelp_banner.png
images/welcome9.svg
uhelp/__init__.py
uhelp/smemo.txt
uhelp/uhelp.ini
uhelp/uhelp.json
uhelp/uhelp.py
uhelp.egg-info/PKG-INFO
uhelp.egg-info/SOURCES.txt
uhelp.egg-info/dependency_links.txt
uhelp.egg-info/entry_points.txt
uhelp.egg-info/requires.txt
uhelp.egg-info/top_level.txt
uhelp/pages/android/am.md
uhelp/pages/android/bugreport.md
uhelp/pages/android/bugreportz.md
uhelp/pages/android/cmd.md
uhelp/pages/android/dalvikvm.md
uhelp/pages/android/dumpsys.md
uhelp/pages/android/getprop.md
uhelp/pages/android/input.md
uhelp/pages/android/logcat.md
uhelp/pages/android/pkg.md
uhelp/pages/android/pm.md
uhelp/pages/android/screencap.md
uhelp/pages/android/settings.md
uhelp/pages/android/wm.md
uhelp/pages/common/!.md
uhelp/pages/common/2to3.md
uhelp/pages/common/7z.md
uhelp/pages/common/7za.md
uhelp/pages/common/7zr.md
uhelp/pages/common/[.md
uhelp/pages/common/[[.md
uhelp/pages/common/^.md
uhelp/pages/common/a2ping.md
uhelp/pages/common/aapt.md
uhelp/pages/common/ab.md
uhelp/pages/common/abduco.md
uhelp/pages/common/ac.md
uhelp/pages/common/accelerate.md
uhelp/pages/common/ack.md
uhelp/pages/common/acme.sh-dns.md
uhelp/pages/common/acme.sh.md
uhelp/pages/common/act.md
uhelp/pages/common/acyclic.md
uhelp/pages/common/adb-install.md
uhelp/pages/common/adb-logcat.md
uhelp/pages/common/adb-reverse.md
uhelp/pages/common/adb-shell.md
uhelp/pages/common/adb.md
uhelp/pages/common/adguardhome.md
uhelp/pages/common/adscript.md
uhelp/pages/common/afconvert.md
uhelp/pages/common/ag.md
uhelp/pages/common/agate.md
uhelp/pages/common/age-keygen.md
uhelp/pages/common/age.md
uhelp/pages/common/aircrack-ng.md
uhelp/pages/common/airdecap-ng.md
uhelp/pages/common/aireplay-ng.md
uhelp/pages/common/airmon-ng.md
uhelp/pages/common/airodump-ng.md
uhelp/pages/common/airpaste.md
uhelp/pages/common/airshare.md
