Metadata-Version: 2.1
Name: uhelp
Version: 0.6.3
Summary: uhelp(pip package) Your own Linux command help dictionary
Home-page: https://github.com/Suletta-Majo/uhelp
Author: Suletta-Majo
Author-email: sulettamajo@gmail.com
License: MIT
Project-URL: Issues, https://github.com/Suletta-Majo/uhelp/issues
License-File: LICENSE
Requires-Dist: ConfigUpdater
Requires-Dist: rich
Requires-Dist: rich-theme-manager
Requires-Dist: tinydb
